slackcat/__init__.py
slackcat/__main__.py
slackcat/compat.py
slackcat/config.py
slackcat/exceptions.py
slackcat/ioutil.py
slackcat/slack.py
slackcat-2.0.0.dist-info/DESCRIPTION.rst
slackcat-2.0.0.dist-info/METADATA
slackcat-2.0.0.dist-info/RECORD
slackcat-2.0.0.dist-info/WHEEL
slackcat-2.0.0.dist-info/entry_points.txt
slackcat-2.0.0.dist-info/metadata.json
slackcat-2.0.0.dist-info/top_level.txt
slackcat-2.0.0.dist-info/zip-safe
