Metadata-Version: 2.0
Name: slackcat
Version: 2.0.0
Summary: Pipe command output to Slack from your terminal!
Home-page: https://github.com/nficano/slackcat
Author: Nick Ficano
Author-email: nficano@gmail.com
License: Copyright (c) 2017 Nick Ficano
